CHANGES.txt
MANIFEST.in
README.txt
setup.py
eggs/lxml-6.0.0-py3.12-win-amd64.egg/EGG-INFO/requires.txt
eggs/lxml-6.0.0-py3.12-win-amd64.egg/EGG-INFO/top_level.txt
eggs/lxml-6.0.0-py3.12-win-amd64.egg/EGG-INFO/licenses/LICENSE.txt
eggs/lxml-6.0.0-py3.12-win-amd64.egg/EGG-INFO/licenses/LICENSES.txt
eggs/lxml-6.0.0-py3.12-win-amd64.egg/lxml/isoschematron/resources/xsl/iso-schematron-xslt1/readme.txt
eggs/p01.checker-0.5.9-py3.12-win-amd64.egg/p01.checker-0.5.9-py3.12-win-amd64.dist-info/LICENSE.txt
eggs/p01.checker-0.5.9-py3.12-win-amd64.egg/p01.checker-0.5.9-py3.12-win-amd64.dist-info/namespace_packages.txt
eggs/p01.checker-0.5.9-py3.12-win-amd64.egg/p01.checker-0.5.9-py3.12-win-amd64.dist-info/top_level.txt
eggs/p01.checker-0.5.9-py3.12-win-amd64.egg/p01/checker/checker.txt
eggs/p01.checker-0.5.9-py3.12-win-amd64.egg/p01/checker/sample/tab.txt
eggs/polib-1.2.0-py3.12.egg/EGG-INFO/top_level.txt
eggs/pyflakes-3.4.0-py3.12.egg/EGG-INFO/entry_points.txt
eggs/pyflakes-3.4.0-py3.12.egg/EGG-INFO/top_level.txt
eggs/zc.recipe.egg-2.0.7-py3.12-win-amd64.egg/zc.recipe.egg-2.0.7-py3.12-win-amd64.dist-info/entry_points.txt
eggs/zc.recipe.egg-2.0.7-py3.12-win-amd64.egg/zc.recipe.egg-2.0.7-py3.12-win-amd64.dist-info/namespace_packages.txt
eggs/zc.recipe.egg-2.0.7-py3.12-win-amd64.egg/zc.recipe.egg-2.0.7-py3.12-win-amd64.dist-info/top_level.txt
eggs/zc.recipe.testrunner-3.2-py3.12.egg/EGG-INFO/LICENSE.txt
eggs/zc.recipe.testrunner-3.2-py3.12.egg/EGG-INFO/entry_points.txt
eggs/zc.recipe.testrunner-3.2-py3.12.egg/EGG-INFO/namespace_packages.txt
eggs/zc.recipe.testrunner-3.2-py3.12.egg/EGG-INFO/requires.txt
eggs/zc.recipe.testrunner-3.2-py3.12.egg/EGG-INFO/top_level.txt
eggs/zope.exceptions-5.2-py3.12.egg/EGG-INFO/LICENSE.txt
eggs/zope.exceptions-5.2-py3.12.egg/EGG-INFO/namespace_packages.txt
eggs/zope.exceptions-5.2-py3.12.egg/EGG-INFO/requires.txt
eggs/zope.exceptions-5.2-py3.12.egg/EGG-INFO/top_level.txt
eggs/zope.interface-7.2-py3.12-win-amd64.egg/EGG-INFO/LICENSE.txt
eggs/zope.interface-7.2-py3.12-win-amd64.egg/EGG-INFO/namespace_packages.txt
eggs/zope.interface-7.2-py3.12-win-amd64.egg/EGG-INFO/requires.txt
eggs/zope.interface-7.2-py3.12-win-amd64.egg/EGG-INFO/top_level.txt
eggs/zope.testing-5.1-py3.12.egg/EGG-INFO/LICENSE.txt
eggs/zope.testing-5.1-py3.12.egg/EGG-INFO/namespace_packages.txt
eggs/zope.testing-5.1-py3.12.egg/EGG-INFO/requires.txt
eggs/zope.testing-5.1-py3.12.egg/EGG-INFO/top_level.txt
eggs/zope.testing-5.1-py3.12.egg/zope/testing/cleanup.txt
eggs/zope.testing-5.1-py3.12.egg/zope/testing/doctestcase.txt
eggs/zope.testing-5.1-py3.12.egg/zope/testing/formparser.txt
eggs/zope.testing-5.1-py3.12.egg/zope/testing/loggingsupport.txt
eggs/zope.testing-5.1-py3.12.egg/zope/testing/module.txt
eggs/zope.testing-5.1-py3.12.egg/zope/testing/renormalizing.txt
eggs/zope.testing-5.1-py3.12.egg/zope/testing/setupstack.txt
eggs/zope.testing-5.1-py3.12.egg/zope/testing/test-1.txt
eggs/zope.testing-5.1-py3.12.egg/zope/testing/test4.txt
eggs/zope.testing-5.1-py3.12.egg/zope/testing/test4e.txt
eggs/zope.testing-5.1-py3.12.egg/zope/testing/test4f.txt
eggs/zope.testing-5.1-py3.12.egg/zope/testing/wait.txt
eggs/zope.testrunner-7.4-py3.12.egg/EGG-INFO/entry_points.txt
eggs/zope.testrunner-7.4-py3.12.egg/EGG-INFO/namespace_packages.txt
eggs/zope.testrunner-7.4-py3.12.egg/EGG-INFO/requires.txt
eggs/zope.testrunner-7.4-py3.12.egg/EGG-INFO/top_level.txt
src/p01/__init__.py
src/p01.buildouthttp.egg-info/PKG-INFO
src/p01.buildouthttp.egg-info/SOURCES.txt
src/p01.buildouthttp.egg-info/dependency_links.txt
src/p01.buildouthttp.egg-info/entry_points.txt
src/p01.buildouthttp.egg-info/namespace_packages.txt
src/p01.buildouthttp.egg-info/not-zip-safe
src/p01.buildouthttp.egg-info/requires.txt
src/p01.buildouthttp.egg-info/top_level.txt
src/p01/buildouthttp/README.txt
src/p01/buildouthttp/__init__.py
src/p01/buildouthttp/buildouthttp.py
src/p01/buildouthttp/checker.txt
src/p01/buildouthttp/tests.py